main.py
llm_mem_ai-0.1.2.dist-info/licenses/LICENSE
mem_ai/__init__.py
mem_ai/env_tools.py
mem_ai/memory.py
mem_ai/ai_platform/__init__.py
mem_ai/ai_platform/plat_base.py
mem_ai/ai_platform/plat_dashscope.py
mem_ai/ai_platform/plat_factory.py
mem_ai/ai_platform/pmot_gen.py
mem_ai/storages/__init__.py
mem_ai/storages/mem_summary.py
mem_ai/storages/mongo_help.py
mem_ai/storages/qdrant_help.py
mem_ai/storages/vector_base.py
mem_ai/storages/vector_factory.py
llm_mem_ai-0.1.2.dist-info/METADATA
llm_mem_ai-0.1.2.dist-info/WHEEL
llm_mem_ai-0.1.2.dist-info/entry_points.txt
llm_mem_ai-0.1.2.dist-info/top_level.txt
llm_mem_ai-0.1.2.dist-info/RECORD
