Metadata-Version: 2.4
Name: llm-mem-ai
Version: 0.1.2
Summary: A LLM Memory Cache package
Author-email: "Jerry.s" <jsduan0813@gmail.com>
License: MIT
Project-URL: Homepage, https://github.com/yourusername/my-awesome-package
Project-URL: Repository, https://github.com/yourusername/my-awesome-package
Project-URL: Documentation, https://my-awesome-package.readthedocs.io/
Project-URL: Bug Tracker, https://github.com/yourusername/my-awesome-package/issues
Keywords: memory,llm,agent
Classifier: Development Status :: 3 - Alpha
Classifier: Intended Audience :: Developers
Classifier: License :: OSI Approved :: MIT License
Classifier: Programming Language :: Python :: 3
Classifier: Programming Language :: Python :: 3.7
Classifier: Programming Language :: Python :: 3.8
Classifier: Programming Language :: Python :: 3.9
Classifier: Programming Language :: Python :: 3.10
Classifier: Programming Language :: Python :: 3.11
Requires-Python: >=3.7
License-File: LICENSE
Requires-Dist: openai==2.14.0
Requires-Dist: pydantic==2.12.5
Requires-Dist: pymongo==4.15.5
Requires-Dist: requests==2.32.5
Requires-Dist: python-dotenv==1.2.1
Requires-Dist: qdrant-client==1.16.2
Requires-Dist: icecream==2.1.8
Provides-Extra: dev
Requires-Dist: pre-commit; extra == "dev"
Requires-Dist: ruff==0.14.10; extra == "dev"
Requires-Dist: import-linter==2.9; extra == "dev"
Requires-Dist: pytest==9.0.2; extra == "dev"
Dynamic: license-file
